LICENSE.txt
MANIFEST.in
README.rst
requirements-dev.txt
setup.cfg
setup.py
Emote.egg-info/SOURCES.txt
emote/__init__.py
emote/core.py
emote/emoji_codes.py
emote.egg-info/PKG-INFO
emote.egg-info/SOURCES.txt
emote.egg-info/dependency_links.txt
emote.egg-info/top_level.txt
emote.egg-info/zip-safe
tests/test_core.py