Metadata-Version: 1.1
Name: Emote
Version: 0.1.1
Summary: Simple emoji lookups for Python.
Home-page: https://github.com/geowurster/Emote
Author: Kevin Wurster
Author-email: wursterk@gmail.com
License: New BSD License
